{
  "GlobalConfiguration": {
    "BaseUrl": "https://localhost:7199",
    "RequestIdKey": "OcRequestId"
  },
  "Routes": [
    {
      "UpstreamPathTemplate": "/api/message",
      "UpstreamHttpMethod": [ "Post" ],
      "DownstreamPathTemplate": "/api/message",
      "DownstreamScheme": "https",
      "DownstreamHostAndPorts": [
        {
          "Host": "localhost",
          "Port": 7127
        }
      ]
    },
    {
      "UpstreamPathTemplate": "/api/ticket",
      "UpstreamHttpMethod": [ "Get" ],
      "DownstreamPathTemplate": "/api/ticket",
      "DownstreamScheme": "https",
      "DownstreamHostAndPorts": [
        {
          "Host": "localhost",
          "Port": 7127
        }
      ]
    },
    {
      "UpstreamPathTemplate": "/api/ticket/{id}",
      "UpstreamHttpMethod": [ "Get" ],
      "DownstreamPathTemplate": "/api/ticket/{id}",
      "DownstreamScheme": "https",
      "DownstreamHostAndPorts": [
        {
          "Host": "localhost",
          "Port": 7127
        }
      ]
    },
    {
      "UpstreamPathTemplate": "/api/user",
      "UpstreamHttpMethod": [ "Post", "Get" ],
      "DownstreamPathTemplate": "/api/user",
      "DownstreamScheme": "https",
      "DownstreamHostAndPorts": [
        {
          "Host": "localhost",
          "Port": 7127
        }
      ]
    },
    {
      "UpstreamPathTemplate": "/api/user/{id}",
      "UpstreamHttpMethod": [ "Put", "Delete", "Get" ],
      "DownstreamPathTemplate": "/api/user/{id}",
      "DownstreamScheme": "https",
      "DownstreamHostAndPorts": [
        {
          "Host": "localhost",
          "Port": 7127
        }
      ]
    }
  ]
}